{
  "Website": "https://sunplussoftware.com/",
  "Institution Type": "Corporates",
  "Location": "Bangalore",
  "Phone": "080 4300 3225",
  "Course": "Programming",
  "Score": 95,
  "Reasoning": "Sunplus Software Technologies is a CMMI Level 5 certified IT services and software development company that specializes in application development, AI/ML solutions, ERP implementation, and digital transformation, indicating a strong technical and programming focus.",
  "extracted_contact_details": [
    {
      "phone": "+91 804 300 3225",
      "email": "info@sunplussoftware.com"
    }
  ]
}