[
  {
    "title": "Sales",
    "phone": "+91 (11) 4674-7700",
    "email": "sales@platinasoft.com"
  },
  {
    "title": "Partners",
    "phone": "+91 (11) 4674-7700",
    "email": "partners@platinasoft.com"
  },
  {
    "title": "Support",
    "phone": "+91 (11) 4674-7700",
    "email": "support@platiansoft.com"
  },
  {
    "title": "Accounts",
    "phone": "+91 (11) 4674-7700",
    "email": "accounts@platinsoft.com"
  },
  {
    "title": "Public Relations",
    "phone": "+91 (11) 4674-7700",
    "email": "pr@platinasoft.com"
  },
  {
    "title": "Legal",
    "phone": "+91 (11) 4674-7700",
    "email": "legal@platinasoft.com"
  },
  {
    "title": "Info",
    "phone": "+91 (11) 4674-7700",
    "email": "info@platinasoft.com"
  }
]