[
  {
    "name": "Alpha Technical Education - Counseling Office",
    "phone": "9313033445, 9582788868"
  },
  {
    "name": "Campus",
    "phone": "9582788868"
  },
  {
    "name": "Dr. Kumar",
    "title": "Admission",
    "phone": "9313033445"
  },
  {
    "name": "Mr. Varun",
    "title": "Examination",
    "phone": "8800028179"
  },
  {
    "name": "Miss Jyoti",
    "title": "Administration",
    "phone": "8800028178"
  },
  {
    "name": "Mrs Manju",
    "title": "Back Office",
    "phone": "8800028177"
  },
  {
    "name": "Quick Contact",
    "phone": "+91-9313033445,9582788868"
  },
  {
    "name": "Quick Contact",
    "phone": "+91-40598505"
  },
  {
    "name": "Quick Contact",
    "phone": "+91-8527394361/62"
  },
  {
    "name": "General Information",
    "phone": "9313033445"
  }
]