[
  {
    "title": "General Enquiry",
    "phone": "011-41718298 / 011-41718299 / 9990937354",
    "email": "info@tiemdelhi.com"
  },
  {
    "title": "Admission Enquiry",
    "phone": "9910225389",
    "email": "admissions@tiemdelhi.com"
  },
  {
    "title": "Placements Enquiry",
    "phone": "9717012303",
    "email": "placements@tiemdelhi.com"
  },
  {
    "name": "Capt. Amardeep Chaudhary",
    "title": "Founder, Managing Director"
  },
  {
    "name": "Mr. Deepak Singh",
    "title": "Academic Director | Centre Head, Faculty of Event Management"
  },
  {
    "name": "Ms. Nidhi Tomar",
    "title": "Director, Faculty of Sports Management"
  },
  {
    "name": "Ms. Monica Mahajan",
    "title": "Event Communication Faculty"
  },
  {
    "name": "Mr. Gurmeet Singh",
    "title": "Event Accounts Faculty"
  },
  {
    "name": "Mr. Luvish Arora",
    "title": "Assistant Lecturer"
  },
  {
    "name": "Ms. Gurpreet Kaur",
    "title": "Assistant Professor"
  },
  {
    "name": "Mr. K. Prashant",
    "title": "Professor"
  },
  {
    "name": "Ms. Vibha Malhotra",
    "title": "Assistant Professor"
  },
  {
    "name": "Dr. P. K. Taneja",
    "title": "Professor"
  },
  {
    "name": "Ms. Sonia Pardasani",
    "title": "Assistant Professor"
  },
  {
    "name": "Ms. Sunita Kharbanda",
    "title": "Assistant Professor"
  },
  {
    "name": "Ms. Simrat Gulati",
    "title": "Assistant Professor"
  },
  {
    "name": "Ms. Shivani Khanna",
    "title": "Assistant Professor"
  },
  {
    "name": "Mr. Lovleen Singh Bhasin",
    "title": "Assistant Professor"
  },
  {
    "name": "Ms. Manpreet Kaur",
    "title": "Senior Career Counsellor"
  },
  {
    "name": "Ms. Pooja Parmar",
    "title": "Senior Career Counsellor"
  },
  {
    "name": "Ms. Rashmi Chaudhary",
    "title": "Career Counsellor"
  },
  {
    "name": "Ms. Karuna Saru",
    "title": "Sr. Placement Coordinator"
  },
  {
    "name": "Ms. Pooja Grover",
    "title": "Sr. Event Coordinator"
  },
  {
    "name": "Ms. Shivani Bakshi",
    "title": "Faculty of Communication & Public Relations"
  },
  {
    "name": "Mr. Narender Kumar",
    "title": "Accounts Head | Faculty of Accounting"
  }
]